namedzip/__init__.py
namedzip/namedzip.py
namedzip-1.1.0.dist-info/LICENSE
namedzip-1.1.0.dist-info/METADATA
namedzip-1.1.0.dist-info/WHEEL
namedzip-1.1.0.dist-info/top_level.txt
namedzip-1.1.0.dist-info/RECORD
