Metadata-Version: 2.1
Name: namedzip
Version: 1.1.0
Summary: Extends zip() and itertools.zip_longest() to generate named tuples.
Home-page: https://github.com/erberlin/namedzip
Author: Erik R Berlin
Author-email: erberlin.dev@gmail.com
License: MIT
Platform: UNKNOWN
Classifier: License :: OSI Approved :: MIT License
Classifier: Programming Language :: Python :: 3
Classifier: Programming Language :: Python :: 3.4
Classifier: Programming Language :: Python :: 3.5
Classifier: Programming Language :: Python :: 3.6
Classifier: Programming Language :: Python :: 3.7
Requires-Python: >=3.4
